cf_validator.py
cf_validator-0.0.5.dist-info/METADATA
cf_validator-0.0.5.dist-info/WHEEL
cf_validator-0.0.5.dist-info/top_level.txt
cf_validator-0.0.5.dist-info/RECORD
